MengyuYishiToushe/Dockerfile
MengyuYishiToushe/README.md
MengyuYishiToushe/__init__.py
MengyuYishiToushe/__main__.py
MengyuYishiToushe/file.epub
MengyuYishiToushe/index.html
MengyuYishiToushe/css/__init__.py
MengyuYishiToushe/css/annotations.css
MengyuYishiToushe/css/main.css
MengyuYishiToushe/css/normalize.css
MengyuYishiToushe/css/popup.css
MengyuYishiToushe/font/__init__.py
MengyuYishiToushe/font/fontello.eot
MengyuYishiToushe/font/fontello.svg
MengyuYishiToushe/font/fontello.ttf
MengyuYishiToushe/font/fontello.woff
MengyuYishiToushe/img/__init__.py
MengyuYishiToushe/img/annotator-glyph-sprite.png
MengyuYishiToushe/img/annotator-icon-sprite.png
MengyuYishiToushe/img/apple-touch-icon.png
MengyuYishiToushe/img/cancelfullscreen.png
MengyuYishiToushe/img/close.png
MengyuYishiToushe/img/fullscreen.png
MengyuYishiToushe/img/loader.gif
MengyuYishiToushe/img/menu-icon.png
MengyuYishiToushe/img/save.png
MengyuYishiToushe/img/saved.png
MengyuYishiToushe/img/settings-s.png
MengyuYishiToushe/img/settings.png
MengyuYishiToushe/img/star.png
MengyuYishiToushe/js/__init__.py
MengyuYishiToushe/js/epub.js
MengyuYishiToushe/js/epub.min.js
MengyuYishiToushe/js/epub.min.map
MengyuYishiToushe/js/hooks.min.js
MengyuYishiToushe/js/hooks.min.map
MengyuYishiToushe/js/reader.js
MengyuYishiToushe/js/reader.js.map
MengyuYishiToushe/js/reader.min.js
MengyuYishiToushe/js/reader.min.map
MengyuYishiToushe/js/hooks/__init__.py
MengyuYishiToushe/js/hooks/extensions/__init__.py
MengyuYishiToushe/js/hooks/extensions/highlight.js
MengyuYishiToushe/js/libs/__init__.py
MengyuYishiToushe/js/libs/jquery.min.js
MengyuYishiToushe/js/libs/localforage.min.js
MengyuYishiToushe/js/libs/screenfull.js
MengyuYishiToushe/js/libs/screenfull.min.js
MengyuYishiToushe/js/libs/zip.min.js
MengyuYishiToushe/js/plugins/__init__.py
MengyuYishiToushe/js/plugins/hypothesis.js
MengyuYishiToushe/js/plugins/search.js
mengyu_yishi_toushe-2022.10.9.1.dist-info/METADATA
mengyu_yishi_toushe-2022.10.9.1.dist-info/WHEEL
mengyu_yishi_toushe-2022.10.9.1.dist-info/entry_points.txt
mengyu_yishi_toushe-2022.10.9.1.dist-info/top_level.txt
mengyu_yishi_toushe-2022.10.9.1.dist-info/RECORD
